{"minified":"composer/2.0","packages":{"yajra/laravel-datatables":[{"name":"yajra/laravel-datatables","description":"Laravel DataTables Complete Package.","keywords":["jquery","laravel","datatables"],"homepage":"","version":"v10.1.0","version_normalized":"10.1.0.0","license":["MIT"],"authors":[{"name":"Arjay Angeles","email":"aqangeles@gmail.com"}],"source":{"url":"https://github.com/yajra/datatables.git","type":"git","reference":"7837d079edd88f088755a62b254e32068dfe16e1"},"dist":{"url":"https://api.github.com/repos/yajra/datatables/zipball/7837d079edd88f088755a62b254e32068dfe16e1","type":"zip","shasum":"","reference":"7837d079edd88f088755a62b254e32068dfe16e1"},"type":"library","funding":[{"url":"https://github.com/sponsors/yajra","type":"github"}],"time":"2023-02-20T05:26:34+00:00","extra":{"branch-alias":{"dev-master":"10.0-dev"}},"require":{"php":"^8.1","yajra/laravel-datatables-buttons":"^10","yajra/laravel-datatables-editor":"1.*","yajra/laravel-datatables-export":"^10","yajra/laravel-datatables-fractal":"^10","yajra/laravel-datatables-html":"^10","yajra/laravel-datatables-oracle":"^10"},"support":{"issues":"https://github.com/yajra/datatables/issues","source":"https://github.com/yajra/datatables/tree/v10.1.0"}},{"version":"v10.0.0","version_normalized":"10.0.0.0","source":{"url":"https://github.com/yajra/datatables.git","type":"git","reference":"5a65f1b611a53a07530915619869ec87dcb823ad"},"dist":{"url":"https://api.github.com/repos/yajra/datatables/zipball/5a65f1b611a53a07530915619869ec87dcb823ad","type":"zip","shasum":"","reference":"5a65f1b611a53a07530915619869ec87dcb823ad"},"time":"2023-02-07T09:44:57+00:00","require":{"php":"^8.1","yajra/laravel-datatables-oracle":"^10","yajra/laravel-datatables-buttons":"^10","yajra/laravel-datatables-editor":"1.*","yajra/laravel-datatables-html":"^10","yajra/laravel-datatables-fractal":"^10"},"support":{"issues":"https://github.com/yajra/datatables/issues","source":"https://github.com/yajra/datatables/tree/v10.0.0"}},{"version":"v9.0.0","version_normalized":"9.0.0.0","source":{"url":"https://github.com/yajra/datatables.git","type":"git","reference":"f16d4c701418d4f60a81e5452933b15b312dde90"},"dist":{"url":"https://api.github.com/repos/yajra/datatables/zipball/f16d4c701418d4f60a81e5452933b15b312dde90","type":"zip","shasum":"","reference":"f16d4c701418d4f60a81e5452933b15b312dde90"},"time":"2022-05-07T16:41:24+00:00","extra":{"branch-alias":{"dev-master":"9.0-dev"}},"require":{"php":"^8.0.2","yajra/laravel-datatables-oracle":"10.*","yajra/laravel-datatables-buttons":"9.*","yajra/laravel-datatables-editor":"1.*","yajra/laravel-datatables-html":"9.*","yajra/laravel-datatables-fractal":"9.*"},"support":{"issues":"https://github.com/yajra/datatables/issues","source":"https://github.com/yajra/datatables/tree/v9.0.0"},"funding":"__unset"},{"version":"v1.5.0","version_normalized":"1.5.0.0","source":{"url":"https://github.com/yajra/datatables.git","type":"git","reference":"50de5e20ef01da1a353e0a81c0ad5f9da6a985ec"},"dist":{"url":"https://api.github.com/repos/yajra/datatables/zipball/50de5e20ef01da1a353e0a81c0ad5f9da6a985ec","type":"zip","shasum":"","reference":"50de5e20ef01da1a353e0a81c0ad5f9da6a985ec"},"time":"2019-02-27T03:17:30+00:00","extra":{"branch-alias":{"dev-master":"1.0-dev"}},"require":{"php":">=7.0","yajra/laravel-datatables-oracle":"8.*|9.*","yajra/laravel-datatables-buttons":"4.*","yajra/laravel-datatables-editor":"1.*","yajra/laravel-datatables-html":"4.*","yajra/laravel-datatables-fractal":"1.*"},"support":{"issues":"https://github.com/yajra/datatables/issues","source":"https://github.com/yajra/datatables/tree/v1.5.0"}},{"version":"v1.4.0","version_normalized":"1.4.0.0","source":{"url":"https://github.com/yajra/datatables.git","type":"git","reference":"f2ed8f557440a6132bd5f4f29382c64b9a2392d4"},"dist":{"url":"https://api.github.com/repos/yajra/datatables/zipball/f2ed8f557440a6132bd5f4f29382c64b9a2392d4","type":"zip","shasum":"","reference":"f2ed8f557440a6132bd5f4f29382c64b9a2392d4"},"time":"2018-11-14T08:42:34+00:00","require":{"php":">=7.0","yajra/laravel-datatables-oracle":"8.*","yajra/laravel-datatables-buttons":"4.*","yajra/laravel-datatables-editor":"1.*","yajra/laravel-datatables-html":"4.*","yajra/laravel-datatables-fractal":"1.*"},"support":{"issues":"https://github.com/yajra/datatables/issues","source":"https://github.com/yajra/datatables/tree/v1.4.0"}},{"version":"v1.3.0","version_normalized":"1.3.0.0","source":{"url":"https://github.com/yajra/datatables.git","type":"git","reference":"78436010aebd6cb7de9111deae0aada789ea4ad5"},"dist":{"url":"https://api.github.com/repos/yajra/datatables/zipball/78436010aebd6cb7de9111deae0aada789ea4ad5","type":"zip","shasum":"","reference":"78436010aebd6cb7de9111deae0aada789ea4ad5"},"time":"2018-11-14T08:34:21+00:00","require":{"php":">=7.0","yajra/laravel-datatables-oracle":"8.*","yajra/laravel-datatables-buttons":"3.*|4.*","yajra/laravel-datatables-editor":"1.*","yajra/laravel-datatables-html":"3.*|4.*","yajra/laravel-datatables-fractal":"1.*"},"support":{"issues":"https://github.com/yajra/datatables/issues","source":"https://github.com/yajra/datatables/tree/v1.3.0"}},{"version":"v1.2.0","version_normalized":"1.2.0.0","source":{"url":"https://github.com/yajra/datatables.git","type":"git","reference":"060c1ef2dc8b3e688852698ca263e6130a2239e5"},"dist":{"url":"https://api.github.com/repos/yajra/datatables/zipball/060c1ef2dc8b3e688852698ca263e6130a2239e5","type":"zip","shasum":"","reference":"060c1ef2dc8b3e688852698ca263e6130a2239e5"},"time":"2018-11-02T03:53:13+00:00","require":{"php":">=7.0","yajra/laravel-datatables-oracle":"8.*","yajra/laravel-datatables-buttons":"3.*|4.*","yajra/laravel-datatables-editor":"1.*","yajra/laravel-datatables-html":"3.*","yajra/laravel-datatables-fractal":"1.*"},"support":{"issues":"https://github.com/yajra/datatables/issues","source":"https://github.com/yajra/datatables/tree/v1.2.0"}},{"version":"v1.1.0","version_normalized":"1.1.0.0","source":{"url":"https://github.com/yajra/datatables.git","type":"git","reference":"a5e2eaac3d7bc155502a37ab490cbcf0dee63e06"},"dist":{"url":"https://api.github.com/repos/yajra/datatables/zipball/a5e2eaac3d7bc155502a37ab490cbcf0dee63e06","type":"zip","shasum":"","reference":"a5e2eaac3d7bc155502a37ab490cbcf0dee63e06"},"time":"2018-08-15T12:31:12+00:00","require":{"php":">=7.0","yajra/laravel-datatables-oracle":"8.*","yajra/laravel-datatables-buttons":"3.*|4.*","yajra/laravel-datatables-html":"3.*","yajra/laravel-datatables-fractal":"1.*"},"support":{"issues":"https://github.com/yajra/datatables/issues","source":"https://github.com/yajra/datatables/tree/v1.1.0"}},{"version":"v1.0.0","version_normalized":"1.0.0.0","source":{"url":"https://github.com/yajra/datatables.git","type":"git","reference":"541481aa26c179ebcbf106fca835e3e3f480b966"},"dist":{"url":"https://api.github.com/repos/yajra/datatables/zipball/541481aa26c179ebcbf106fca835e3e3f480b966","type":"zip","shasum":"","reference":"541481aa26c179ebcbf106fca835e3e3f480b966"},"time":"2017-08-31T02:05:46+00:00","require":{"php":">=7.0","yajra/laravel-datatables-oracle":"8.*","yajra/laravel-datatables-buttons":"3.*","yajra/laravel-datatables-html":"3.*","yajra/laravel-datatables-fractal":"1.*"},"support":{"issues":"https://github.com/yajra/datatables/issues","source":"https://github.com/yajra/datatables/tree/v1.0.0"}}]},"security-advisories":[],"last-modified":"Mon, 20 Feb 2023 05:26:52 GMT"}